{"HeroId":38,"CurrentTile":2,"Hero":{"id":38,"playerId":"","name":"jenny","heroClass":"Ranger","gender":"Female","remainingHitPointsPercentage":45.853658536585385,"totalHitPoints":40.0,"remainingHitPoints":18.3,"baseSkillPoints":12,"usedUpSkillPoints":10,"isAscended":false,"rarity":5,"prestigeLevel":0,"level":1,"experiencePoints":4,"dailyQuestsUsed":0,"remainingQuests":900,"skills":[{"methodName":"apply_skill_barbed_projectile","slug":"skill-barbed-projectile","name":"Barbed Projectile","description":"Deals 1D6 damage and deals an additional 1D4 damage per round for 2 rounds.","skillClass":"Ranger","requiredSkillPoints":3,"allocatedSkillPoints":0,"skillUseInstance":[{"id":"26abdead-90b5-49dd-a321-38311fb74249","alreadyUsed":true},{"id":"bf27ffdd-ba4b-434f-99e4-2f69c94e3dff","alreadyUsed":true}],"skillsCalculatedStats":{"TotalUses":0,"CurrentUsesRemaining":0},"id":"7218d1ae-e0f6-4e32-a3ba-875c81d9157f","type":"LearnedHeroSkill"},{"methodName":"apply_skill_herbal_knowledge","slug":"skill-herbal-knowledge","name":"Herbal Knowledge","description":"Heals 3HP and gives 20% Dodge for 2 rounds.","skillClass":"Ranger","requiredSkillPoints":4,"allocatedSkillPoints":0,"skillUseInstance":[{"id":"90c31e9d-29be-43fc-8803-2b49b760cce9","alreadyUsed":true}],"skillsCalculatedStats":{"TotalUses":0,"CurrentUsesRemaining":0},"id":"d9e67524-292f-4d92-b638-cfb6273b80e6","type":"LearnedHeroSkill"}],"zoneBackgroundType":0,"unsecuredDCXValue":{"amount":0.0,"withdrawlOrderId":null},"generation":0,"baseChanceToHit":0,"baseHitPoints":40,"isHearthstoneAvailable":true,"maxExperiencePoints":20,"maxDailyQuests":15,"learnedSkillCapacity":6,"difficultyToHit":2500,"inventory":[{"id":"38140b1b-e18f-439c-8f5e-eb7284796cde","nftTokenId":0,"itemIndex":null,"rarity":"Common","armorMitigation":200,"armorMitigationAmount":1,"parryRate":0,"dodgeRate":0,"criticalHitRate":0,"bonusDamage":0,"affectedAttributes":{"Strength":0},"slug":"ill-fitted-sandals","name":"Ill Fitted Sandals","itemDropSound":"sandals","slot":"feet","dieDamage":[],"heroStatComplianceDictionary":{},"allowedHeroClassList":["Warrior","Ranger","Mage"],"imageSlug":"rough-slippers","type":"ItemDto"},{"id":"14930603-ea83-479d-8d36-4f04a81425c2","nftTokenId":0,"itemIndex":null,"rarity":"Common","armorMitigation":1169,"armorMitigationAmount":1,"parryRate":0,"dodgeRate":0,"criticalHitRate":0,"bonusDamage":0,"affectedAttributes":{"HitPoints":0},"slug":"strong-guard's-helm","name":"Strong Guard's Helm","itemDropSound":"metal-helm","slot":"head","dieDamage":[],"heroStatComplianceDictionary":{},"allowedHeroClassList":["Warrior","Ranger","Mage"],"imageSlug":"strong-guard's-helm","type":"ItemDto"},{"id":"ec4d24b3-6616-46a0-84bf-e13c84f58384","nftTokenId":0,"itemIndex":null,"rarity":"Unknown","armorMitigation":1054,"armorMitigationAmount":0,"parryRate":0,"dodgeRate":0,"criticalHitRate":0,"bonusDamage":0,"affectedAttributes":{"Quickness":0},"slug":"strong-guard's-helm","name":"Strong Guard's Helm","itemDropSound":"metal-helm","slot":"head","dieDamage":[],"heroStatComplianceDictionary":{},"allowedHeroClassList":["Warrior","Ranger","Mage"],"imageSlug":"strong-guard's-helm","type":"ItemDto"},{"id":"7ffa0311-f323-462c-b690-c85c5e501e37","nftTokenId":0,"itemIndex":null,"rarity":"Unknown","armorMitigation":0,"armorMitigationAmount":0,"parryRate":0,"dodgeRate":85,"criticalHitRate":0,"bonusDamage":0,"affectedAttributes":{"HitPoints":0},"slug":"rough-slippers","name":"Rough Slippers","itemDropSound":"sandals","slot":"feet","dieDamage":[],"heroStatComplianceDictionary":{},"allowedHeroClassList":["Warrior","Ranger","Mage"],"imageSlug":"rough-slippers","type":"ItemDto"},{"id":"d4c8f03d-cc73-436f-b37e-f05852d2f364","nftTokenId":0,"itemIndex":null,"rarity":"Unknown","armorMitigation":1082,"armorMitigationAmount":0,"parryRate":0,"dodgeRate":0,"criticalHitRate":0,"bonusDamage":0,"affectedAttributes":{"Agility":0},"slug":"strong-guard's-helm","name":"Strong Guard's Helm","itemDropSound":"metal-helm","slot":"head","dieDamage":[],"heroStatComplianceDictionary":{},"allowedHeroClassList":["Warrior","Ranger","Mage"],"imageSlug":"strong-guard's-helm","type":"ItemDto"},{"id":"98938b5d-a0f1-4a1c-b919-e7327f98561d","nftTokenId":0,"itemIndex":null,"rarity":"Common","armorMitigation":100,"armorMitigationAmount":1,"parryRate":0,"dodgeRate":0,"criticalHitRate":0,"bonusDamage":0,"affectedAttributes":{"Wisdom":0},"slug":"unironically-hideous-cap","name":"Unironically Hideous Cap","itemDropSound":"cloth-head","slot":"head","dieDamage":[],"heroStatComplianceDictionary":{},"allowedHeroClassList":["Warrior","Ranger","Mage"],"imageSlug":"leather-cap","type":"ItemDto"},{"id":"0b7678b7-f326-4404-acd2-a5f8f737831f","nftTokenId":0,"itemIndex":null,"rarity":"Unknown","armorMitigation":0,"armorMitigationAmount":0,"parryRate":0,"dodgeRate":0,"criticalHitRate":0,"bonusDamage":0,"affectedAttributes":{"HitPoints":0},"slug":"simple-shortsword","name":"Simple Shortsword","itemDropSound":"metal-weapon","slot":"mainHand","dieDamage":[{"Sides":6}],"heroStatComplianceDictionary":{},"allowedHeroClassList":["Ranger"],"imageSlug":"simple-shortsword","type":"ItemDto"},{"id":"e24eaf1a-0d89-45db-97f6-d2d42006af08","nftTokenId":0,"itemIndex":null,"rarity":"Common","armorMitigation":400,"armorMitigationAmount":0,"parryRate":0,"dodgeRate":0,"criticalHitRate":0,"bonusDamage":0,"affectedAttributes":{"Quickness":0},"slug":"hand-me-down-leathers","name":"Hand me down Leathers","itemDropSound":"leathers","slot":"chest","dieDamage":[],"heroStatComplianceDictionary":{},"allowedHeroClassList":["Warrior","Ranger","Mage"],"imageSlug":"broken-in-leathers","type":"ItemDto"}],"equippedItems":[],"calculatedStats":{"strength":9,"agility":16,"wisdom":8,"quickness":5,"charisma":9,"chanceToCrit":240,"chanceToParry":160,"chanceToHit":0,"difficultyToHit":2500,"chanceToDodge":180,"armorMitigation":90,"armorMitigationAmount":0,"itemBonusDamage":0,"statsBonusDamage":3,"damageRange":{"lower":3,"upper":6}},"heroLevelUpProps":{},"strength":9,"agility":16,"wisdom":8,"quickness":5,"charisma":9},"CurrentEncounters":[],"HighestZoneVisited":"wildPrairie","itemsToMoveToStash":[{"id":"49945582-5788-4365-b848-62bdf8bc1399","nftTokenId":0,"itemIndex":null,"rarity":"Uncommon","armorMitigation":0,"armorMitigationAmount":0,"parryRate":15,"dodgeRate":47,"criticalHitRate":100,"bonusDamage":0,"affectedAttributes":{"Agility":1},"slug":"dexterous-commoner's-band","name":"Dexterous Commoner's Band","itemDropSound":"ring","slot":"ring","dieDamage":[],"heroStatComplianceDictionary":{},"allowedHeroClassList":["Warrior","Ranger","Mage"],"imageSlug":"dexterous-commoner's-band","type":"ItemDto"},{"id":"6cb78004-4d88-404a-b649-20126a7d10a0","nftTokenId":0,"itemIndex":null,"rarity":"Uncommon","armorMitigation":0,"armorMitigationAmount":1,"parryRate":0,"dodgeRate":75,"criticalHitRate":0,"bonusDamage":0,"affectedAttributes":{"HitPoints":1},"slug":"rough-slippers","name":"Rough Slippers","itemDropSound":"sandals","slot":"feet","dieDamage":[],"heroStatComplianceDictionary":{},"allowedHeroClassList":["Warrior","Ranger","Mage"],"imageSlug":"rough-slippers","type":"ItemDto"},{"id":"ef1a187b-934b-4c9d-9c4c-fc946595e738","nftTokenId":0,"itemIndex":null,"rarity":"Unknown","armorMitigation":0,"armorMitigationAmount":0,"parryRate":21,"dodgeRate":22,"criticalHitRate":60,"bonusDamage":0,"affectedAttributes":{"Strength":0},"slug":"stubborn-iron-ring","name":"Stubborn Iron Ring","itemDropSound":"ring","slot":"ring","dieDamage":[],"heroStatComplianceDictionary":{},"allowedHeroClassList":["Warrior","Ranger","Mage"],"imageSlug":"stubborn-iron-ring","type":"ItemDto"},{"id":"a12c97bb-29fe-45b6-bf7f-127fab74cdb4","nftTokenId":0,"itemIndex":null,"rarity":"Unknown","armorMitigation":0,"armorMitigationAmount":0,"parryRate":21,"dodgeRate":41,"criticalHitRate":94,"bonusDamage":0,"affectedAttributes":{"Wisdom":0},"slug":"dexterous-commoner's-band","name":"Dexterous Commoner's Band","itemDropSound":"ring","slot":"ring","dieDamage":[],"heroStatComplianceDictionary":{},"allowedHeroClassList":["Warrior","Ranger","Mage"],"imageSlug":"dexterous-commoner's-band","type":"ItemDto"},{"id":"efc69c56-9179-4f3a-bb37-6816ac53e9df","nftTokenId":0,"itemIndex":null,"rarity":"Rare","armorMitigation":0,"armorMitigationAmount":1,"parryRate":0,"dodgeRate":68,"criticalHitRate":0,"bonusDamage":0,"affectedAttributes":{"Quickness":2},"slug":"rough-slippers","name":"Rough Slippers","itemDropSound":"sandals","slot":"feet","dieDamage":[],"heroStatComplianceDictionary":{},"allowedHeroClassList":["Warrior","Ranger","Mage"],"imageSlug":"rough-slippers","type":"ItemDto"},{"id":"75c8370d-fd67-4d32-af73-3f9c80468cca","nftTokenId":0,"itemIndex":null,"rarity":"Rare","armorMitigation":0,"armorMitigationAmount":0,"parryRate":57,"dodgeRate":50,"criticalHitRate":59,"bonusDamage":0,"affectedAttributes":{"Strength":2},"slug":"dexterous-commoner's-band","name":"Dexterous Commoner's Band","itemDropSound":"ring","slot":"ring","dieDamage":[],"heroStatComplianceDictionary":{},"allowedHeroClassList":["Warrior","Ranger","Mage"],"imageSlug":"dexterous-commoner's-band","type":"ItemDto"},{"id":"d85e089b-448d-4b86-90c7-4764998d7354","nftTokenId":0,"itemIndex":null,"rarity":"Unknown","armorMitigation":0,"armorMitigationAmount":0,"parryRate":0,"dodgeRate":0,"criticalHitRate":0,"bonusDamage":0,"affectedAttributes":{"Charisma":0},"slug":"yew-crossbow","name":"Yew Crossbow","itemDropSound":"crossbow","slot":"twoHand","dieDamage":[{"Sides":10}],"heroStatComplianceDictionary":{},"allowedHeroClassList":["Ranger"],"imageSlug":"yew-crossbow","type":"ItemDto"},{"id":"6dcd2ae3-4a23-4ce2-9377-c4c22af698d6","nftTokenId":0,"itemIndex":null,"rarity":"Uncommon","armorMitigation":0,"armorMitigationAmount":1,"parryRate":0,"dodgeRate":91,"criticalHitRate":0,"bonusDamage":0,"affectedAttributes":{"Wisdom":1},"slug":"very-fine-hat","name":"Very Fine Hat","itemDropSound":"cloth-head","slot":"head","dieDamage":[],"heroStatComplianceDictionary":{},"allowedHeroClassList":["Warrior","Ranger","Mage"],"imageSlug":"very-fine-hat","type":"ItemDto"},{"id":"efc69c56-9179-4f3a-bb37-6816ac53e9df","nftTokenId":0,"itemIndex":null,"rarity":"Rare","armorMitigation":0,"armorMitigationAmount":1,"parryRate":0,"dodgeRate":68,"criticalHitRate":0,"bonusDamage":0,"affectedAttributes":{"Quickness":2},"slug":"rough-slippers","name":"Rough Slippers","itemDropSound":"sandals","slot":"feet","dieDamage":[],"heroStatComplianceDictionary":{},"allowedHeroClassList":["Warrior","Ranger","Mage"],"imageSlug":"rough-slippers","type":"ItemDto"}],"inactiveDailyTiles":[],"inactiveBossTiles":[]}